fontfinder/__init__.py
fontfinder/_generate_ref_data.py
fontfinder/filters.py
fontfinder/model.py
fontfinder/noto.py
fontfinder/__pyinstaller/__init__.py
fontfinder/__pyinstaller/hook-fontfinder.py
fontfinder/_platforms/__init__.py
fontfinder/_platforms/mac.py
fontfinder/_platforms/windows.py
fontfinder/data/noto.json
fontfinder/data/scriptMetadata.json
fontfinder/data/small_unihan.json
fontfinder-0.16.1.dist-info/licenses/LICENSE
fontfinder-0.16.1.dist-info/METADATA
fontfinder-0.16.1.dist-info/WHEEL
fontfinder-0.16.1.dist-info/entry_points.txt
fontfinder-0.16.1.dist-info/top_level.txt
fontfinder-0.16.1.dist-info/RECORD
