Metadata-Version: 2.4
Name: fontfinder
Version: 0.16.1
Summary: Package for finding and installing fonts for Unicode scripts.
Project-URL: Documentation, https://multiscript.app/fontfinder
Project-URL: Source, https://github.com/multiscript/fontfinder
Project-URL: Issue Tracker, https://github.com/multiscript/fontfinder/issues
Classifier: Programming Language :: Python :: 3
Classifier: License :: OSI Approved :: MIT License
Classifier: Operating System :: OS Independent
Classifier: Development Status :: 4 - Beta
Classifier: Intended Audience :: Developers
Requires-Python: >=3.10
License-File: LICENSE
Requires-Dist: comtypes>=1.4.11; platform_system == "Windows"
Requires-Dist: packaging>=25.0
Requires-Dist: platformdirs>=4.3.8
Requires-Dist: requests>=2.32.5
Requires-Dist: unicodedataplus>=16.0.0.post1
Provides-Extra: test
Requires-Dist: pytest; extra == "test"
Provides-Extra: docs
Requires-Dist: pdoc; extra == "docs"
Provides-Extra: unihan
Requires-Dist: unihan-etl>=0.37; extra == "unihan"
Requires-Dist: typing_extensions; extra == "unihan"
Dynamic: license-file
